{
  "C:\\usr\\work\\javaProject\\javaApp-005-DesignPattern\\GoF-Design-Pattern\\designpattern\\src": {
    "location": "C:\\usr\\work\\javaProject\\javaApp-005-DesignPattern\\GoF-Design-Pattern\\designpattern\\src",
    "status": "UNRESOLVED",
    "error": "No class path info available for \u0027C:\\usr\\work\\javaProject\\javaApp-005-DesignPattern\\GoF-Design-Pattern\\designpattern\\src\u0027. Skipped."
  },
  "C:\\Program Files\\Java\\jdk1.7.0_13\\jre\\lib\\rt.jar": {
    "coordinate": "jre:jre:zip:call:1.0.0",
    "location": "C:\\Program Files\\Java\\jdk1.7.0_13\\jre\\lib\\rt.jar",
    "status": "RESOLVED",
    "error": "No class path info available for \u0027C:\\Program Files\\Java\\jdk1.7.0_13\\jre\\lib\\rt.jar\u0027. Skipped."
  }
}